{
  "location": {
    "name": "Ca Mau",
    "region": "",
    "country": "Vietnam",
    "lat": 9.177,
    "lon": 105.15,
    "tz_id": "Asia/Ho_Chi_Minh",
    "localtime_epoch": 1774698231,
    "localtime": "2026-03-28 18:43"
  },
  "forecast": {
    "forecastday": [
      {
        "date": "2025-01-02",
        "date_epoch": 1735776000,
        "day": {
          "maxtemp_c": 29.2,
          "maxtemp_f": 84.5,
          "mintemp_c": 23.8,
          "mintemp_f": 74.9,
          "avgtemp_c": 25.9,
          "avgtemp_f": 78.5,
          "maxwind_mph": 5.4,
          "maxwind_kph": 8.6,
          "totalprecip_mm": 0.0,
          "totalprecip_in": 0.0,
          "totalsnow_cm": 0.0,
          "avgvis_km": 10.0,
          "avgvis_miles": 6.0,
          "avghumidity": 72,
          "daily_will_it_rain": 0,
          "daily_chance_of_rain": 0,
          "daily_will_it_snow": 0,
          "daily_chance_of_snow": 0,
          "condition": {
            "text": "Cloudy",
            "icon": "//cdn.weatherapi.com/weather/64x64/day/119.png",
            "code": 1006
          },
          "uv": 4.2
        },
        "astro": {
          "sunrise": "06:15 AM",
          "sunset": "05:52 PM",
          "moonrise": "08:14 AM",
          "moonset": "08:10 PM",
          "moon_phase": "Waxing Crescent",
          "moon_illumination": 4
        },
        "hour": [
          {
            "time_epoch": 1735750800,
            "time": "2025-01-02 00:00",
            "temp_c": 24.1,
            "temp_f": 75.4,
            "is_day": 0,
            "condition": {
              "text": "Overcast",
              "icon": "//cdn.weatherapi.com/weather/64x64/night/122.png",
              "code": 1009
            },
            "wind_mph": 2.5,
            "wind_kph": 4.0,
            "wind_degree": 39,
            "wind_dir": "NE",
            "pressure_mb": 1010.0,
            "pressure_in": 29.84,
            "precip_mm": 0.0,
            "precip_in": 0.0,
            "snow_cm": 0.0,
            "humidity": 78,
            "cloud": 86,
            "feelslike_c": 26.0,
            "feelslike_f": 78.8,
            "windchill_c": 24.1,
            "windchill_f": 75.4,
            "heatindex_c": 26.0,
            "heatindex_f": 78.8,
            "dewpoint_c": 20.1,
            "dewpoint_f": 68.2,
            "will_it_rain": 0,
            "chance_of_rain": 0,
            "will_it_snow": 0,
            "chance_of_snow": 0,
            "vis_km": 10.0,
            "vis_miles": 6.0,
            "gust_mph": 4.2,
            "gust_kph": 6.7,
            "uv": 0.0
          },
          {
            "time_epoch": 1735754400,
            "time": "2025-01-02 01:00",
            "temp_c": 24.3,
            "temp_f": 75.8,
            "is_day": 0,
            "condition": {
              "text": "Overcast",
              "icon": "//cdn.weatherapi.com/weather/64x64/night/122.png",
              "code": 1009
            },
            "wind_mph": 2.5,
            "wind_kph": 4.0,
            "wind_degree": 19,
            "wind_dir": "NNE",
            "pressure_mb": 1010.0,
            "pressure_in": 29.82,
            "precip_mm": 0.0,
            "precip_in": 0.0,
            "snow_cm": 0.0,
            "humidity": 77,
            "cloud": 100,
            "feelslike_c": 26.2,
            "feelslike_f": 79.1,
            "windchill_c": 24.3,
            "windchill_f": 75.8,
            "heatindex_c": 26.2,
            "heatindex_f": 79.1,
            "dewpoint_c": 20.1,
            "dewpoint_f": 68.2,
            "will_it_rain": 0,
            "chance_of_rain": 0,
            "will_it_snow": 0,
            "chance_of_snow": 0,
            "vis_km": 10.0,
            "vis_miles": 6.0,
            "gust_mph": 4.0,
            "gust_kph": 6.5,
            "uv": 0.0
          },
          {
            "time_epoch": 1735758000,
            "time": "2025-01-02 02:00",
            "temp_c": 24.2,
            "temp_f": 75.5,
            "is_day": 0,
            "condition": {
              "text": "Overcast",
              "icon": "//cdn.weatherapi.com/weather/64x64/night/122.png",
              "code": 1009
            },
            "wind_mph": 3.4,
            "wind_kph": 5.4,
            "wind_degree": 2,
            "wind_dir": "N",
            "pressure_mb": 1009.0,
            "pressure_in": 29.8,
            "precip_mm": 0.0,
            "precip_in": 0.0,
            "snow_cm": 0.0,
            "humidity": 78,
            "cloud": 89,
            "feelslike_c": 26.0,
            "feelslike_f": 78.9,
            "windchill_c": 24.2,
            "windchill_f": 75.5,
            "heatindex_c": 26.0,
            "heatindex_f": 78.9,
            "dewpoint_c": 20.1,
            "dewpoint_f": 68.2,
            "will_it_rain": 0,
            "chance_of_rain": 0,
            "will_it_snow": 0,
            "chance_of_snow": 0,
            "vis_km": 10.0,
            "vis_miles": 6.0,
            "gust_mph": 5.6,
            "gust_kph": 9.0,
            "uv": 0.0
          },
          {
            "time_epoch": 1735761600,
            "time": "2025-01-02 03:00",
            "temp_c": 23.9,
            "temp_f": 75.1,
            "is_day": 0,
            "condition": {
              "text": "Overcast",
              "icon": "//cdn.weatherapi.com/weather/64x64/night/122.png",
              "code": 1009
            },
            "wind_mph": 3.4,
            "wind_kph": 5.4,
            "wind_degree": 18,
            "wind_dir": "NNE",
            "pressure_mb": 1009.0,
            "pressure_in": 29.79,
            "precip_mm": 0.0,
            "precip_in": 0.0,
            "snow_cm": 0.0,
            "humidity": 79,
            "cloud": 93,
            "feelslike_c": 25.8,
            "feelslike_f": 78.5,
            "windchill_c": 23.9,
            "windchill_f": 75.1,
            "heatindex_c": 25.8,
            "heatindex_f": 78.5,
            "dewpoint_c": 20.1,
            "dewpoint_f": 68.3,
            "will_it_rain": 0,
            "chance_of_rain": 0,
            "will_it_snow": 0,
            "chance_of_snow": 0,
            "vis_km": 10.0,
            "vis_miles": 6.0,
            "gust_mph": 5.7,
            "gust_kph": 9.3,
            "uv": 0.0
          },
          {
            "time_epoch": 1735765200,
            "time": "2025-01-02 04:00",
            "temp_c": 23.8,
            "temp_f": 74.9,
            "is_day": 0,
            "condition": {
              "text": "Overcast",
              "icon": "//cdn.weatherapi.com/weather/64x64/night/122.png",
              "code": 1009
            },
            "wind_mph": 2.7,
            "wind_kph": 4.3,
            "wind_degree": 13,
            "wind_dir": "NNE",
            "pressure_mb": 1009.0,
            "pressure_in": 29.79,
            "precip_mm": 0.0,
            "precip_in": 0.0,
            "snow_cm": 0.0,
            "humidity": 80,
            "cloud": 100,
            "feelslike_c": 25.8,
            "feelslike_f": 78.4,
            "windchill_c": 23.8,
            "windchill_f": 74.9,
            "heatindex_c": 25.8,
            "heatindex_f": 78.4,
            "dewpoint_c": 20.2,
            "dewpoint_f": 68.3,
            "will_it_rain": 0,
            "chance_of_rain": 0,
            "will_it_snow": 0,
            "chance_of_snow": 0,
            "vis_km": 10.0,
            "vis_miles": 6.0,
            "gust_mph": 4.6,
            "gust_kph": 7.4,
            "uv": 0.0
          },
          {
            "time_epoch": 1735768800,
            "time": "2025-01-02 05:00",
            "temp_c": 23.8,
            "temp_f": 74.9,
            "is_day": 0,
            "condition": {
              "text": "Overcast",
              "icon": "//cdn.weatherapi.com/weather/64x64/night/122.png",
              "code": 1009
            },
            "wind_mph": 2.5,
            "wind_kph": 4.0,
            "wind_degree": 356,
            "wind_dir": "N",
            "pressure_mb": 1009.0,
            "pressure_in": 29.8,
            "precip_mm": 0.0,
            "precip_in": 0.0,
            "snow_cm": 0.0,
            "humidity": 80,
            "cloud": 100,
            "feelslike_c": 25.8,
            "feelslike_f": 78.4,
            "windchill_c": 23.8,
            "windchill_f": 74.9,
            "heatindex_c": 25.8,
            "heatindex_f": 78.4,
            "dewpoint_c": 20.2,
            "dewpoint_f": 68.4,
            "will_it_rain": 0,
            "chance_of_rain": 0,
            "will_it_snow": 0,
            "chance_of_snow": 0,
            "vis_km": 10.0,
            "vis_miles": 6.0,
            "gust_mph": 4.2,
            "gust_kph": 6.8,
            "uv": 0.0
          },
          {
            "time_epoch": 1735772400,
            "time": "2025-01-02 06:00",
            "temp_c": 24.0,
            "temp_f": 75.2,
            "is_day": 0,
            "condition": {
              "text": "Partly cloudy",
              "icon": "//cdn.weatherapi.com/weather/64x64/night/116.png",
              "code": 1003
            },
            "wind_mph": 2.7,
            "wind_kph": 4.3,
            "wind_degree": 353,
            "wind_dir": "N",
            "pressure_mb": 1010.0,
            "pressure_in": 29.82,
            "precip_mm": 0.0,
            "precip_in": 0.0,
            "snow_cm": 0.0,
            "humidity": 80,
            "cloud": 40,
            "feelslike_c": 25.9,
            "feelslike_f": 78.7,
            "windchill_c": 24.0,
            "windchill_f": 75.2,
            "heatindex_c": 25.9,
            "heatindex_f": 78.7,
            "dewpoint_c": 20.3,
            "dewpoint_f": 68.6,
            "will_it_rain": 0,
            "chance_of_rain": 0,
            "will_it_snow": 0,
            "chance_of_snow": 0,
            "vis_km": 10.0,
            "vis_miles": 6.0,
            "gust_mph": 4.5,
            "gust_kph": 7.2,
            "uv": 0.0
          },
          {
            "time_epoch": 1735776000,
            "time": "2025-01-02 07:00",
            "temp_c": 24.1,
            "temp_f": 75.5,
            "is_day": 1,
            "condition": {
              "text": "Partly cloudy",
              "icon": "//cdn.weatherapi.com/weather/64x64/day/116.png",
              "code": 1003
            },
            "wind_mph": 3.4,
            "wind_kph": 5.4,
            "wind_degree": 355,
            "wind_dir": "N",
            "pressure_mb": 1011.0,
            "pressure_in": 29.84,
            "precip_mm": 0.0,
            "precip_in": 0.0,
            "snow_cm": 0.0,
            "humidity": 80,
            "cloud": 38,
            "feelslike_c": 26.1,
            "feelslike_f": 78.9,
            "windchill_c": 24.1,
            "windchill_f": 75.5,
            "heatindex_c": 26.1,
            "heatindex_f": 78.9,
            "dewpoint_c": 20.5,
            "dewpoint_f": 68.8,
            "will_it_rain": 0,
            "chance_of_rain": 0,
            "will_it_snow": 0,
            "chance_of_snow": 0,
            "vis_km": 10.0,
            "vis_miles": 6.0,
            "gust_mph": 5.5,
            "gust_kph": 8.8,
            "uv": 0.0
          },
          {
            "time_epoch": 1735779600,
            "time": "2025-01-02 08:00",
            "temp_c": 24.7,
            "temp_f": 76.4,
            "is_day": 1,
            "condition": {
              "text": "Partly cloudy",
              "icon": "//cdn.weatherapi.com/weather/64x64/day/116.png",
              "code": 1003
            },
            "wind_mph": 3.6,
            "wind_kph": 5.8,
            "wind_degree": 353,
            "wind_dir": "N",
            "pressure_mb": 1012.0,
            "pressure_in": 29.87,
            "precip_mm": 0.0,
            "precip_in": 0.0,
            "snow_cm": 0.0,
            "humidity": 78,
            "cloud": 42,
            "feelslike_c": 26.6,
            "feelslike_f": 79.8,
            "windchill_c": 24.7,
            "windchill_f": 76.4,
            "heatindex_c": 26.6,
            "heatindex_f": 79.8,
            "dewpoint_c": 20.6,
            "dewpoint_f": 69.2,
            "will_it_rain": 0,
            "chance_of_rain": 0,
            "will_it_snow": 0,
            "chance_of_snow": 0,
            "vis_km": 10.0,
            "vis_miles": 6.0,
            "gust_mph": 8.2,
            "gust_kph": 13.2,
            "uv": 0.2
          },
          {
            "time_epoch": 1735783200,
            "time": "2025-01-02 09:00",
            "temp_c": 26.4,
            "temp_f": 79.4,
            "is_day": 1,
            "condition": {
              "text": "Partly cloudy",
              "icon": "//cdn.weatherapi.com/weather/64x64/day/116.png",
              "code": 1003
            },
            "wind_mph": 4.5,
            "wind_kph": 7.2,
            "wind_degree": 344,
            "wind_dir": "NNW",
            "pressure_mb": 1012.0,
            "pressure_in": 29.89,
            "precip_mm": 0.0,
            "precip_in": 0.0,
            "snow_cm": 0.0,
            "humidity": 74,
            "cloud": 47,
            "feelslike_c": 28.5,
            "feelslike_f": 83.4,
            "windchill_c": 26.4,
            "windchill_f": 79.4,
            "heatindex_c": 28.5,
            "heatindex_f": 83.4,
            "dewpoint_c": 21.2,
            "dewpoint_f": 70.2,
            "will_it_rain": 0,
            "chance_of_rain": 0,
            "will_it_snow": 0,
            "chance_of_snow": 0,
            "vis_km": 10.0,
            "vis_miles": 6.0,
            "gust_mph": 10.4,
            "gust_kph": 16.7,
            "uv": 1.2
          },
          {
            "time_epoch": 1735786800,
            "time": "2025-01-02 10:00",
            "temp_c": 26.9,
            "temp_f": 80.5,
            "is_day": 1,
            "condition": {
              "text": "Partly cloudy",
              "icon": "//cdn.weatherapi.com/weather/64x64/day/116.png",
              "code": 1003
            },
            "wind_mph": 5.4,
            "wind_kph": 8.6,
            "wind_degree": 349,
            "wind_dir": "N",
            "pressure_mb": 1012.0,
            "pressure_in": 29.87,
            "precip_mm": 0.0,
            "precip_in": 0.0,
            "snow_cm": 0.0,
            "humidity": 69,
            "cloud": 38,
            "feelslike_c": 29.1,
            "feelslike_f": 84.3,
            "windchill_c": 26.9,
            "windchill_f": 80.5,
            "heatindex_c": 29.1,
            "heatindex_f": 84.3,
            "dewpoint_c": 20.9,
            "dewpoint_f": 69.7,
            "will_it_rain": 0,
            "chance_of_rain": 0,
            "will_it_snow": 0,
            "chance_of_snow": 0,
            "vis_km": 10.0,
            "vis_miles": 6.0,
            "gust_mph": 11.4,
            "gust_kph": 18.4,
            "uv": 3.8
          },
          {
            "time_epoch": 1735790400,
            "time": "2025-01-02 11:00",
            "temp_c": 27.7,
            "temp_f": 81.8,
            "is_day": 1,
            "condition": {
              "text": "Partly cloudy",
              "icon": "//cdn.weatherapi.com/weather/64x64/day/116.png",
              "code": 1003
            },
            "wind_mph": 4.7,
            "wind_kph": 7.6,
            "wind_degree": 352,
            "wind_dir": "N",
            "pressure_mb": 1011.0,
            "pressure_in": 29.86,
            "precip_mm": 0.0,
            "precip_in": 0.0,
            "snow_cm": 0.0,
            "humidity": 65,
            "cloud": 33,
            "feelslike_c": 29.9,
            "feelslike_f": 85.8,
            "windchill_c": 27.7,
            "windchill_f": 81.8,
            "heatindex_c": 29.9,
            "heatindex_f": 85.8,
            "dewpoint_c": 20.8,
            "dewpoint_f": 69.5,
            "will_it_rain": 0,
            "chance_of_rain": 0,
            "will_it_snow": 0,
            "chance_of_snow": 0,
            "vis_km": 10.0,
            "vis_miles": 6.0,
            "gust_mph": 11.4,
            "gust_kph": 18.4,
            "uv": 6.4
          },
          {
            "time_epoch": 1735794000,
            "time": "2025-01-02 12:00",
            "temp_c": 27.4,
            "temp_f": 81.3,
            "is_day": 1,
            "condition": {
              "text": "Cloudy",
              "icon": "//cdn.weatherapi.com/weather/64x64/day/119.png",
              "code": 1006
            },
            "wind_mph": 4.7,
            "wind_kph": 7.6,
            "wind_degree": 340,
            "wind_dir": "NNW",
            "pressure_mb": 1010.0,
            "pressure_in": 29.83,
            "precip_mm": 0.0,
            "precip_in": 0.0,
            "snow_cm": 0.0,
            "humidity": 62,
            "cloud": 76,
            "feelslike_c": 29.0,
            "feelslike_f": 84.3,
            "windchill_c": 27.4,
            "windchill_f": 81.3,
            "heatindex_c": 29.0,
            "heatindex_f": 84.3,
            "dewpoint_c": 19.4,
            "dewpoint_f": 67.0,
            "will_it_rain": 0,
            "chance_of_rain": 0,
            "will_it_snow": 0,
            "chance_of_snow": 0,
            "vis_km": 10.0,
            "vis_miles": 6.0,
            "gust_mph": 11.4,
            "gust_kph": 18.4,
            "uv": 2.7
          },
          {
            "time_epoch": 1735797600,
            "time": "2025-01-02 13:00",
            "temp_c": 28.5,
            "temp_f": 83.3,
            "is_day": 1,
            "condition": {
              "text": "Cloudy",
              "icon": "//cdn.weatherapi.com/weather/64x64/day/119.png",
              "code": 1006
            },
            "wind_mph": 4.9,
            "wind_kph": 7.9,
            "wind_degree": 328,
            "wind_dir": "NNW",
            "pressure_mb": 1009.0,
            "pressure_in": 29.8,
            "precip_mm": 0.0,
            "precip_in": 0.0,
            "snow_cm": 0.0,
            "humidity": 59,
            "cloud": 64,
            "feelslike_c": 30.3,
            "feelslike_f": 86.6,
            "windchill_c": 28.5,
            "windchill_f": 83.3,
            "heatindex_c": 30.3,
            "heatindex_f": 86.6,
            "dewpoint_c": 19.6,
            "dewpoint_f": 67.3,
            "will_it_rain": 0,
            "chance_of_rain": 0,
            "will_it_snow": 0,
            "chance_of_snow": 0,
            "vis_km": 10.0,
            "vis_miles": 6.0,
            "gust_mph": 10.8,
            "gust_kph": 17.5,
            "uv": 3.7
          },
          {
            "time_epoch": 1735801200,
            "time": "2025-01-02 14:00",
            "temp_c": 29.2,
            "temp_f": 84.5,
            "is_day": 1,
            "condition": {
              "text": "Partly cloudy",
              "icon": "//cdn.weatherapi.com/weather/64x64/day/116.png",
              "code": 1003
            },
            "wind_mph": 4.3,
            "wind_kph": 6.8,
            "wind_degree": 333,
            "wind_dir": "NNW",
            "pressure_mb": 1008.0,
            "pressure_in": 29.76,
            "precip_mm": 0.0,
            "precip_in": 0.0,
            "snow_cm": 0.0,
            "humidity": 57,
            "cloud": 58,
            "feelslike_c": 31.2,
            "feelslike_f": 88.2,
            "windchill_c": 29.2,
            "windchill_f": 84.5,
            "heatindex_c": 31.2,
            "heatindex_f": 88.2,
            "dewpoint_c": 19.8,
            "dewpoint_f": 67.7,
            "will_it_rain": 0,
            "chance_of_rain": 0,
            "will_it_snow": 0,
            "chance_of_snow": 0,
            "vis_km": 10.0,
            "vis_miles": 6.0,
            "gust_mph": 10.4,
            "gust_kph": 16.8,
            "uv": 2.8
          },
          {
            "time_epoch": 1735804800,
            "time": "2025-01-02 15:00",
            "temp_c": 29.0,
            "temp_f": 84.3,
            "is_day": 1,
            "condition": {
              "text": "Cloudy",
              "icon": "//cdn.weatherapi.com/weather/64x64/day/119.png",
              "code": 1006
            },
            "wind_mph": 3.8,
            "wind_kph": 6.1,
            "wind_degree": 16,
            "wind_dir": "NNE",
            "pressure_mb": 1007.0,
            "pressure_in": 29.74,
            "precip_mm": 0.0,
            "precip_in": 0.0,
            "snow_cm": 0.0,
            "humidity": 59,
            "cloud": 73,
            "feelslike_c": 31.2,
            "feelslike_f": 88.2,
            "windchill_c": 29.0,
            "windchill_f": 84.3,
            "heatindex_c": 31.2,
            "heatindex_f": 88.2,
            "dewpoint_c": 20.1,
            "dewpoint_f": 68.3,
            "will_it_rain": 0,
            "chance_of_rain": 0,
            "will_it_snow": 0,
            "chance_of_snow": 0,
            "vis_km": 10.0,
            "vis_miles": 6.0,
            "gust_mph": 10.3,
            "gust_kph": 16.5,
            "uv": 0.7
          },
          {
            "time_epoch": 1735808400,
            "time": "2025-01-02 16:00",
            "temp_c": 28.6,
            "temp_f": 83.5,
            "is_day": 1,
            "condition": {
              "text": "Partly cloudy",
              "icon": "//cdn.weatherapi.com/weather/64x64/day/116.png",
              "code": 1003
            },
            "wind_mph": 4.0,
            "wind_kph": 6.5,
            "wind_degree": 36,
            "wind_dir": "NE",
            "pressure_mb": 1007.0,
            "pressure_in": 29.75,
            "precip_mm": 0.0,
            "precip_in": 0.0,
            "snow_cm": 0.0,
            "humidity": 61,
            "cloud": 60,
            "feelslike_c": 30.8,
            "feelslike_f": 87.5,
            "windchill_c": 28.6,
            "windchill_f": 83.5,
            "heatindex_c": 30.8,
            "heatindex_f": 87.5,
            "dewpoint_c": 20.4,
            "dewpoint_f": 68.8,
            "will_it_rain": 0,
            "chance_of_rain": 0,
            "will_it_snow": 0,
            "chance_of_snow": 0,
            "vis_km": 10.0,
            "vis_miles": 6.0,
            "gust_mph": 10.5,
            "gust_kph": 16.9,
            "uv": 0.2
          },
          {
            "time_epoch": 1735812000,
            "time": "2025-01-02 17:00",
            "temp_c": 27.7,
            "temp_f": 81.9,
            "is_day": 1,
            "condition": {
              "text": "Partly cloudy",
              "icon": "//cdn.weatherapi.com/weather/64x64/day/116.png",
              "code": 1003
            },
            "wind_mph": 3.1,
            "wind_kph": 5.0,
            "wind_degree": 38,
            "wind_dir": "NE",
            "pressure_mb": 1008.0,
            "pressure_in": 29.76,
            "precip_mm": 0.0,
            "precip_in": 0.0,
            "snow_cm": 0.0,
            "humidity": 66,
            "cloud": 49,
            "feelslike_c": 30.0,
            "feelslike_f": 85.9,
            "windchill_c": 27.7,
            "windchill_f": 81.9,
            "heatindex_c": 30.0,
            "heatindex_f": 85.9,
            "dewpoint_c": 20.8,
            "dewpoint_f": 69.4,
            "will_it_rain": 0,
            "chance_of_rain": 0,
            "will_it_snow": 0,
            "chance_of_snow": 0,
            "vis_km": 10.0,
            "vis_miles": 6.0,
            "gust_mph": 9.2,
            "gust_kph": 14.9,
            "uv": 0.0
          },
          {
            "time_epoch": 1735815600,
            "time": "2025-01-02 18:00",
            "temp_c": 26.2,
            "temp_f": 79.1,
            "is_day": 0,
            "condition": {
              "text": "Partly cloudy",
              "icon": "//cdn.weatherapi.com/weather/64x64/night/116.png",
              "code": 1003
            },
            "wind_mph": 2.2,
            "wind_kph": 3.6,
            "wind_degree": 50,
            "wind_dir": "NE",
            "pressure_mb": 1008.0,
            "pressure_in": 29.77,
            "precip_mm": 0.0,
            "precip_in": 0.0,
            "snow_cm": 0.0,
            "humidity": 72,
            "cloud": 44,
            "feelslike_c": 28.2,
            "feelslike_f": 82.7,
            "windchill_c": 26.2,
            "windchill_f": 79.1,
            "heatindex_c": 28.2,
            "heatindex_f": 82.7,
            "dewpoint_c": 20.8,
            "dewpoint_f": 69.3,
            "will_it_rain": 0,
            "chance_of_rain": 0,
            "will_it_snow": 0,
            "chance_of_snow": 0,
            "vis_km": 10.0,
            "vis_miles": 6.0,
            "gust_mph": 7.5,
            "gust_kph": 12.0,
            "uv": 0.0
          },
          {
            "time_epoch": 1735819200,
            "time": "2025-01-02 19:00",
            "temp_c": 25.7,
            "temp_f": 78.3,
            "is_day": 0,
            "condition": {
              "text": "Partly cloudy",
              "icon": "//cdn.weatherapi.com/weather/64x64/night/116.png",
              "code": 1003
            },
            "wind_mph": 2.0,
            "wind_kph": 3.2,
            "wind_degree": 84,
            "wind_dir": "E",
            "pressure_mb": 1009.0,
            "pressure_in": 29.79,
            "precip_mm": 0.0,
            "precip_in": 0.0,
            "snow_cm": 0.0,
            "humidity": 74,
            "cloud": 39,
            "feelslike_c": 27.6,
            "feelslike_f": 81.8,
            "windchill_c": 25.7,
            "windchill_f": 78.3,
            "heatindex_c": 27.6,
            "heatindex_f": 81.8,
            "dewpoint_c": 20.7,
            "dewpoint_f": 69.3,
            "will_it_rain": 0,
            "chance_of_rain": 0,
            "will_it_snow": 0,
            "chance_of_snow": 0,
            "vis_km": 10.0,
            "vis_miles": 6.0,
            "gust_mph": 6.3,
            "gust_kph": 10.2,
            "uv": 0.0
          },
          {
            "time_epoch": 1735822800,
            "time": "2025-01-02 20:00",
            "temp_c": 25.3,
            "temp_f": 77.5,
            "is_day": 0,
            "condition": {
              "text": "Partly cloudy",
              "icon": "//cdn.weatherapi.com/weather/64x64/night/116.png",
              "code": 1003
            },
            "wind_mph": 1.6,
            "wind_kph": 2.5,
            "wind_degree": 99,
            "wind_dir": "E",
            "pressure_mb": 1010.0,
            "pressure_in": 29.82,
            "precip_mm": 0.0,
            "precip_in": 0.0,
            "snow_cm": 0.0,
            "humidity": 76,
            "cloud": 41,
            "feelslike_c": 27.2,
            "feelslike_f": 81.0,
            "windchill_c": 25.3,
            "windchill_f": 77.5,
            "heatindex_c": 27.2,
            "heatindex_f": 81.0,
            "dewpoint_c": 20.7,
            "dewpoint_f": 69.2,
            "will_it_rain": 0,
            "chance_of_rain": 0,
            "will_it_snow": 0,
            "chance_of_snow": 0,
            "vis_km": 10.0,
            "vis_miles": 6.0,
            "gust_mph": 3.0,
            "gust_kph": 4.8,
            "uv": 0.0
          },
          {
            "time_epoch": 1735826400,
            "time": "2025-01-02 21:00",
            "temp_c": 25.0,
            "temp_f": 77.0,
            "is_day": 0,
            "condition": {
              "text": "Partly cloudy",
              "icon": "//cdn.weatherapi.com/weather/64x64/night/116.png",
              "code": 1003
            },
            "wind_mph": 1.3,
            "wind_kph": 2.2,
            "wind_degree": 86,
            "wind_dir": "E",
            "pressure_mb": 1011.0,
            "pressure_in": 29.84,
            "precip_mm": 0.0,
            "precip_in": 0.0,
            "snow_cm": 0.0,
            "humidity": 77,
            "cloud": 46,
            "feelslike_c": 26.9,
            "feelslike_f": 80.5,
            "windchill_c": 25.0,
            "windchill_f": 77.0,
            "heatindex_c": 26.9,
            "heatindex_f": 80.5,
            "dewpoint_c": 20.6,
            "dewpoint_f": 69.2,
            "will_it_rain": 0,
            "chance_of_rain": 0,
            "will_it_snow": 0,
            "chance_of_snow": 0,
            "vis_km": 10.0,
            "vis_miles": 6.0,
            "gust_mph": 2.6,
            "gust_kph": 4.2,
            "uv": 0.0
          },
          {
            "time_epoch": 1735830000,
            "time": "2025-01-02 22:00",
            "temp_c": 25.0,
            "temp_f": 77.0,
            "is_day": 0,
            "condition": {
              "text": "Partly cloudy",
              "icon": "//cdn.weatherapi.com/weather/64x64/night/116.png",
              "code": 1003
            },
            "wind_mph": 0.9,
            "wind_kph": 1.4,
            "wind_degree": 79,
            "wind_dir": "E",
            "pressure_mb": 1010.0,
            "pressure_in": 29.84,
            "precip_mm": 0.0,
            "precip_in": 0.0,
            "snow_cm": 0.0,
            "humidity": 77,
            "cloud": 49,
            "feelslike_c": 26.9,
            "feelslike_f": 80.5,
            "windchill_c": 25.0,
            "windchill_f": 77.0,
            "heatindex_c": 26.9,
            "heatindex_f": 80.5,
            "dewpoint_c": 20.7,
            "dewpoint_f": 69.2,
            "will_it_rain": 0,
            "chance_of_rain": 0,
            "will_it_snow": 0,
            "chance_of_snow": 0,
            "vis_km": 10.0,
            "vis_miles": 6.0,
            "gust_mph": 1.7,
            "gust_kph": 2.7,
            "uv": 0.0
          },
          {
            "time_epoch": 1735833600,
            "time": "2025-01-02 23:00",
            "temp_c": 25.0,
            "temp_f": 77.0,
            "is_day": 0,
            "condition": {
              "text": "Partly cloudy",
              "icon": "//cdn.weatherapi.com/weather/64x64/night/116.png",
              "code": 1003
            },
            "wind_mph": 0.7,
            "wind_kph": 1.1,
            "wind_degree": 33,
            "wind_dir": "NE",
            "pressure_mb": 1010.0,
            "pressure_in": 29.82,
            "precip_mm": 0.0,
            "precip_in": 0.0,
            "snow_cm": 0.0,
            "humidity": 77,
            "cloud": 54,
            "feelslike_c": 27.0,
            "feelslike_f": 80.5,
            "windchill_c": 25.0,
            "windchill_f": 77.0,
            "heatindex_c": 27.0,
            "heatindex_f": 80.5,
            "dewpoint_c": 20.7,
            "dewpoint_f": 69.3,
            "will_it_rain": 0,
            "chance_of_rain": 0,
            "will_it_snow": 0,
            "chance_of_snow": 0,
            "vis_km": 10.0,
            "vis_miles": 6.0,
            "gust_mph": 1.3,
            "gust_kph": 2.0,
            "uv": 0.0
          }
        ]
      }
    ]
  }
}